integrity_rating_pending/__init__.py
integrity_rating_pending/_nbdev.py
integrity_rating_pending/core.py
integrity_rating_pending-1.0.1.dist-info/LICENSE
integrity_rating_pending-1.0.1.dist-info/METADATA
integrity_rating_pending-1.0.1.dist-info/WHEEL
integrity_rating_pending-1.0.1.dist-info/top_level.txt
integrity_rating_pending-1.0.1.dist-info/RECORD
