Metadata-Version: 2.1
Name: integrity-rating-pending
Version: 1.0.1
Summary: Please set the integrity rating of this package to pending
Home-page: https://github.com/fabge/integrity_rating_pending/tree/main/
Author: Fabian
Author-email: geiger.fabian@outlook.com
License: Apache Software License 2.0
Keywords: integrity rating,pending
Platform: UNKNOWN
Classifier: Development Status :: 3 - Alpha
Classifier: Intended Audience :: Developers
Classifier: Natural Language :: English
Classifier: Programming Language :: Python :: 3.6
Classifier: Programming Language :: Python :: 3.7
Classifier: Programming Language :: Python :: 3.8
Classifier: Programming Language :: Python :: 3.9
Classifier: Programming Language :: Python :: 3.10
Classifier: License :: OSI Approved :: Apache Software License
Requires-Python: >=3.6
License-File: LICENSE
Requires-Dist: pip
Requires-Dist: packaging
Provides-Extra: dev
